google_language_support/__init__.py
google_language_support-0.3.0.dist-info/LICENSE
google_language_support-0.3.0.dist-info/METADATA
google_language_support-0.3.0.dist-info/WHEEL
google_language_support-0.3.0.dist-info/RECORD
