Metadata-Version: 2.3
Name: google-language-support
Version: 0.3.0
Summary: Google language support
License: MIT
Author: Allen Chou
Author-email: f1470891079@gmail.com
Requires-Python: >=3.11,<4
Classifier: License :: OSI Approved :: MIT License
Classifier: Programming Language :: Python :: 3
Classifier: Programming Language :: Python :: 3.11
Classifier: Programming Language :: Python :: 3.12
Classifier: Programming Language :: Python :: 3.13
